gitverse/__init__.py
gitverse/commits.py
gitverse/help.py
gitverse/releases.py
gitverse/requirements.txt
gitverse/models/auth_bearer.py
gitverse/models/callables.py
gitverse/models/debugger.py
gitverse/utils/rst.py
gitverse-3.3.dist-info/licenses/LICENSE
gitverse-3.3.dist-info/METADATA
gitverse-3.3.dist-info/WHEEL
gitverse-3.3.dist-info/entry_points.txt
gitverse-3.3.dist-info/top_level.txt
gitverse-3.3.dist-info/RECORD
