Metadata-Version: 2.4
Name: gitverse
Version: 3.3
Summary: Get GitHub's release notes or commit history and format it into `reStructuredText`/`Markdown` documents.
Author-email: Vignesh Rao <svignesh1793@gmail.com>
License: MIT License
Project-URL: Homepage, https://github.com/thevickypedia/gitverse
Project-URL: Docs, https://thevickypedia.github.io/gitverse/
Project-URL: Source, https://github.com/thevickypedia/gitverse
Project-URL: Bug Tracker, https://github.com/thevickypedia/gitverse/issues
Project-URL: Release Notes, https://github.com/thevickypedia/gitverse/blob/main/release_notes.rst
Keywords: changelog,automate,commits,releases
Classifier: Development Status :: 5 - Production/Stable
Classifier: Intended Audience :: Developers
Classifier: License :: OSI Approved :: MIT License
Classifier: Programming Language :: Python :: 3 :: Only
Classifier: Topic :: Software Development :: Version Control :: Git
Classifier: Operating System :: OS Independent
Classifier: Topic :: Software Development :: Documentation
Requires-Python: >=3.8
License-File: LICENSE
Requires-Dist: click
Requires-Dist: requests
Requires-Dist: python-dotenv
Provides-Extra: dev
Requires-Dist: pre-commit; extra == "dev"
Requires-Dist: xmltodict; extra == "dev"
Dynamic: license-file
